geass/__init__.py
geass/db.py
geass/main.py
geass/models.py
geass/remote.py
geass/utils.py
geass-0.2.2.dist-info/METADATA
geass-0.2.2.dist-info/WHEEL
geass-0.2.2.dist-info/entry_points.txt
geass-0.2.2.dist-info/licenses/LICENSE
geass-0.2.2.dist-info/RECORD
