Metadata-Version: 2.4
Name: geass
Version: 0.2.2
Summary: Opinionated CLI for generating transcripts to use with LLMs
Project-URL: Homepage, https://github.com/Kabilan108/geass
Author-email: Tony Kabilan Okeke <tonykabilanokeke@gmail.com>
License-Expression: MIT
License-File: LICENSE
Requires-Python: >=3.10
Requires-Dist: faster-whisper>=1.1.1
Requires-Dist: fastlite>=0.1.2
Requires-Dist: modal>=0.73.92
Requires-Dist: mutagen>=1.47.0
Requires-Dist: pydantic==2.6.4
Requires-Dist: rich==13.7.1
Requires-Dist: torch>=2.6.0
Requires-Dist: typer>=0.15.0
